code_ingest/__init__.py
code_ingest/__main__.py
code_ingest/ingest_server.py
code_ingest/pipeline.py
docker-build/Dockerfile
setup-code/0.sh
setup-code/0blank.sh
tests/__init__.py
tests/apply_kernel_tunables_sysctl.sh
tests/functionality_check.py
code_ingest-0.7.0.dist-info/entry_points.txt
code_ingest-0.7.0.dist-info/LICENSE
code_ingest-0.7.0.dist-info/WHEEL
code_ingest-0.7.0.dist-info/METADATA
code_ingest-0.7.0.dist-info/RECORD
