Metadata-Version: 2.1
Name: code-ingest
Version: 0.7.0
Summary: This runs code in a time-limited, offline docker container and returns the results.
Home-page: https://github.com/ractf/code-ingest
License: AGPL-3.0-only
Author: RACTF Contributors
Requires-Python: >=3.9,<4.0
Classifier: Environment :: Web Environment
Classifier: Intended Audience :: Education
Classifier: Intended Audience :: Information Technology
Classifier: License :: OSI Approved :: GNU Affero General Public License v3
Classifier: Programming Language :: Python :: 3
Classifier: Programming Language :: Python :: 3.9
Classifier: Topic :: Internet :: WWW/HTTP :: WSGI
Classifier: Topic :: Security
Classifier: Topic :: Software Development
Requires-Dist: docker
Requires-Dist: starlette
Requires-Dist: uvicorn
Project-URL: Repository, https://github.com/ractf/code-ingest
